[
  {
    "pk": 2,
    "model": "accounts.batch",
    "fields": {
      "finishtime": null,
      "name": "Image Labeling",
      "value": 0.01,
      "numtask": 106,
      "bclass": "extract",
      "runtask": 0,
      "done": false,
      "deadline": "2013-09-25T11:47:49Z",
      "repetition": 3,
      "pulication": "2013-09-25T11:47:49Z",
      "description": "Enter a list of keywords that describe the objects in the image bellow"
    }
  },
  {
    "pk": 201,
    "model": "accounts.task",
    "fields": {
      "lock": 3,
      "question": "1205b017cdc13c41a25413b1f30aec04eda336aac290a27db0b1988e670be56c.jpg",
      "batch": 2,
      "done": 0,
      "choice": ""
    }
  },
  {
    "pk": 202,
    "model": "accounts.task",
    "fields": {
      "lock": 3,
      "question": "16dadc726bea33d2a578fbcb5160aa4febdcc2422e08aac9c893b2c01ac5be70.jpg",
      "batch": 2,
      "done": 0,
      "choice": ""
    }
  },
  {
    "pk": 203,
    "model": "accounts.task",
    "fields": {
      "lock": 3,
      "question": "1cd6c442d4efe647a6afa2d0ec722c5d39f385bbb919d3b63d10faa9d98aad1e.jpg",
      "batch": 2,
      "done": 0,
      "choice": ""
    }
  },
  {
    "pk": 204,
    "model": "accounts.task",
    "fields": {
      "lock": 3,
      "question": "1cf76ce72ec3e831f64b59e83bbe21643ba0b3fbc9b5af5de59a0c1a5975c88e.jpg",
      "batch": 2,
      "done": 0,
      "choice": ""
    }
  },
  {
    "pk": 205,
    "model": "accounts.task",
    "fields": {
      "lock": 3,
      "question": "2269c3b458f3f66c1a48f7816299c2e752e19177890288888e4585c77b93909e.jpg",
      "batch": 2,
      "done": 0,
      "choice": ""
    }
  },
  {
    "pk": 206,
    "model": "accounts.task",
    "fields": {
      "lock": 3,
      "question": "22e5878ca16978f520fb205e2ef3cb825dd6c98897ba975ddd6a6707b1cf564a.jpg",
      "batch": 2,
      "done": 0,
      "choice": ""
    }
  },
  {
    "pk": 207,
    "model": "accounts.task",
    "fields": {
      "lock": 3,
      "question": "29d2af714d26021abd89c3942908a8c7b687230cd24095220d58eb5a31cbb067.jpg",
      "batch": 2,
      "done": 0,
      "choice": ""
    }
  },
  {
    "pk": 208,
    "model": "accounts.task",
    "fields": {
      "lock": 3,
      "question": "2aa7dd3d9f9151ee3295163077f0f949b1188f9ab7c72875641bee7067153062.jpg",
      "batch": 2,
      "done": 0,
      "choice": ""
    }
  },
  {
    "pk": 209,
    "model": "accounts.task",
    "fields": {
      "lock": 3,
      "question": "2ec4a2533f3b4d5b6253b8b750bae1d54d1c39116078b370a8865980129112c9.jpg",
      "batch": 2,
      "done": 0,
      "choice": ""
    }
  },
  {
    "pk": 210,
    "model": "accounts.task",
    "fields": {
      "lock": 3,
      "question": "2ec9b6f4ae2f569cab0ea96c688fa37e7a8d1bbfcd5efc6a217647cdd5556da8.jpg",
      "batch": 2,
      "done": 0,
      "choice": ""
    }
  },
  {
    "pk": 211,
    "model": "accounts.task",
    "fields": {
      "lock": 3,
      "question": "30685f60b03d93b9ecf8f8681d7a9131e55e41b2b6776f41ec8146f7e20c5bb2.jpg",
      "batch": 2,
      "done": 0,
      "choice": ""
    }
  },
  {
    "pk": 212,
    "model": "accounts.task",
    "fields": {
      "lock": 3,
      "question": "35f21d7cb6a4bc61bc3d5926b19ffecbb51d7aca300fe7029cc27a5bd1fdf1c8.jpg",
      "batch": 2,
      "done": 0,
      "choice": ""
    }
  },
  {
    "pk": 213,
    "model": "accounts.task",
    "fields": {
      "lock": 3,
      "question": "364f78581dedff449ad40441b94d466409f8a58d805d1ac8aa3528d870850e27.jpg",
      "batch": 2,
      "done": 0,
      "choice": ""
    }
  },
  {
    "pk": 214,
    "model": "accounts.task",
    "fields": {
      "lock": 3,
      "question": "382bc3dd2fd9ebf2d9ec6dbebb1d8b5e94beb3d1b6daca04b6bac0d219d41dee.jpg",
      "batch": 2,
      "done": 0,
      "choice": ""
    }
  },
  {
    "pk": 215,
    "model": "accounts.task",
    "fields": {
      "lock": 3,
      "question": "39fedd377609a6768c71e11283805d00ebb2e10ce9d836d0f1eb618f5fb842da.jpg",
      "batch": 2,
      "done": 0,
      "choice": ""
    }
  },
  {
    "pk": 216,
    "model": "accounts.task",
    "fields": {
      "lock": 3,
      "question": "3bd6acf2b4d456e9710793ddf9d2319ba67c37ec7a68e524c5fe4418b9481a01.jpg",
      "batch": 2,
      "done": 0,
      "choice": ""
    }
  },
  {
    "pk": 217,
    "model": "accounts.task",
    "fields": {
      "lock": 3,
      "question": "3c602b72cc6895718f5a0ef2091098eb219ad5e9c0bb5cf880483c64a0e74502.jpg",
      "batch": 2,
      "done": 0,
      "choice": ""
    }
  },
  {
    "pk": 218,
    "model": "accounts.task",
    "fields": {
      "lock": 3,
      "question": "3ce18a184ca90392843594cb554c8429dd03600f1a96916ea3ff9d7ec63df370.jpg",
      "batch": 2,
      "done": 0,
      "choice": ""
    }
  },
  {
    "pk": 219,
    "model": "accounts.task",
    "fields": {
      "lock": 3,
      "question": "45208b4bc2330c3d2ae38552bc1c893d0e05cf98d449f783bb0ede7f4271a4eb.jpg",
      "batch": 2,
      "done": 0,
      "choice": ""
    }
  },
  {
    "pk": 220,
    "model": "accounts.task",
    "fields": {
      "lock": 3,
      "question": "48d5af071bfa382ccbb097d5a68370ae047726c9b2277fd64f06523f2675e863.jpg",
      "batch": 2,
      "done": 0,
      "choice": ""
    }
  },
  {
    "pk": 221,
    "model": "accounts.task",
    "fields": {
      "lock": 3,
      "question": "4abcbf33345c742b09fc5aad6ffb3802689532c92d2f93b8b40a2b2c1d6b1b74.jpg",
      "batch": 2,
      "done": 0,
      "choice": ""
    }
  },
  {
    "pk": 222,
    "model": "accounts.task",
    "fields": {
      "lock": 3,
      "question": "4d96c3493a2d3ddd995a0708e329cc16f135f36b1f54b20adf34642d8ed4580d.jpg",
      "batch": 2,
      "done": 0,
      "choice": ""
    }
  },
  {
    "pk": 223,
    "model": "accounts.task",
    "fields": {
      "lock": 3,
      "question": "50e67859164750fa5369759fb2a6c59288cb208c826e4fba4ff0cc81c1316097.jpg",
      "batch": 2,
      "done": 0,
      "choice": ""
    }
  },
  {
    "pk": 224,
    "model": "accounts.task",
    "fields": {
      "lock": 3,
      "question": "514854f366103bdfc9117790cc067cd089bbefbc9d34786639b7b79d526320ec.jpg",
      "batch": 2,
      "done": 0,
      "choice": ""
    }
  },
  {
    "pk": 225,
    "model": "accounts.task",
    "fields": {
      "lock": 3,
      "question": "51e38492afdcdb2a5d92c864ac92623ac1265e6bd1af98cb095f03f15c785d5d.jpg",
      "batch": 2,
      "done": 0,
      "choice": ""
    }
  },
  {
    "pk": 226,
    "model": "accounts.task",
    "fields": {
      "lock": 3,
      "question": "527ca0a8646aa2750d89df7895525fed370750bc9dd6918eac7b09c5501d97b1.jpg",
      "batch": 2,
      "done": 0,
      "choice": ""
    }
  },
  {
    "pk": 227,
    "model": "accounts.task",
    "fields": {
      "lock": 3,
      "question": "5327832eac95f5ff7f004e7a889b507c816e50deeb05c40a4bbc7b97d46fe6d9.jpg",
      "batch": 2,
      "done": 0,
      "choice": ""
    }
  },
  {
    "pk": 228,
    "model": "accounts.task",
    "fields": {
      "lock": 3,
      "question": "5414389f7507ad2fe8a22e0d4b207daed3adc4f17474fe9b4bb672a069162158.jpg",
      "batch": 2,
      "done": 0,
      "choice": ""
    }
  },
  {
    "pk": 229,
    "model": "accounts.task",
    "fields": {
      "lock": 3,
      "question": "5707889037c9ca628c5388fcc519b51849989c23e18a6546fc9bd25b37c02b82.jpg",
      "batch": 2,
      "done": 0,
      "choice": ""
    }
  },
  {
    "pk": 230,
    "model": "accounts.task",
    "fields": {
      "lock": 3,
      "question": "584f553bdf85a648a750b1c11bd58f074ea550bc24641a8ffe05bfd217566391.jpg",
      "batch": 2,
      "done": 0,
      "choice": ""
    }
  },
  {
    "pk": 231,
    "model": "accounts.task",
    "fields": {
      "lock": 3,
      "question": "58a17f050525a08d1571113b750858590a0a0be0c4329157fabe61b1f89c6ab2.jpg",
      "batch": 2,
      "done": 0,
      "choice": ""
    }
  },
  {
    "pk": 232,
    "model": "accounts.task",
    "fields": {
      "lock": 3,
      "question": "5a9df08f9a7dfb3cf6ae2c0c4333d56ac4ea2e6e76b6aff8d935e8c5f6563683.jpg",
      "batch": 2,
      "done": 0,
      "choice": ""
    }
  },
  {
    "pk": 233,
    "model": "accounts.task",
    "fields": {
      "lock": 3,
      "question": "5b0ba6149a1c319e19b49c1f49f4b966ea06373ab5556ddb49ca450b86b09c24.jpg",
      "batch": 2,
      "done": 0,
      "choice": ""
    }
  },
  {
    "pk": 234,
    "model": "accounts.task",
    "fields": {
      "lock": 3,
      "question": "6068001a74265607ef28d21c15a504321823d8aaf5a28b5fae9cb7c1f6d3f668.jpg",
      "batch": 2,
      "done": 0,
      "choice": ""
    }
  },
  {
    "pk": 235,
    "model": "accounts.task",
    "fields": {
      "lock": 3,
      "question": "6120a551424b421b4bca68516ecd1cb4a8ca4716e0767cfc3f8ceda40ad89210.jpg",
      "batch": 2,
      "done": 0,
      "choice": ""
    }
  },
  {
    "pk": 236,
    "model": "accounts.task",
    "fields": {
      "lock": 3,
      "question": "61f18720e95384b081f3d5361d39ff29a9be244828b5c053086b1138d5c6ea17.jpg",
      "batch": 2,
      "done": 0,
      "choice": ""
    }
  },
  {
    "pk": 237,
    "model": "accounts.task",
    "fields": {
      "lock": 3,
      "question": "62dbccdebf3174265215bb0e6f1c43f0cd4a0efb552144dd04f1f0b6a4ae8b34.jpg",
      "batch": 2,
      "done": 0,
      "choice": ""
    }
  },
  {
    "pk": 238,
    "model": "accounts.task",
    "fields": {
      "lock": 3,
      "question": "645acf05fe33c40adc50072a432bd9bc9ba1c92f8210e3eaf40ad8e6c08c7d55.jpg",
      "batch": 2,
      "done": 0,
      "choice": ""
    }
  },
  {
    "pk": 239,
    "model": "accounts.task",
    "fields": {
      "lock": 3,
      "question": "741d4ce3eab7874450b5ff9be94d8c70bef178046a04577fbfd817455ac32263.jpg",
      "batch": 2,
      "done": 0,
      "choice": ""
    }
  },
  {
    "pk": 240,
    "model": "accounts.task",
    "fields": {
      "lock": 3,
      "question": "750cc685f13360a4e896a5edcca8e7d448f2e93a8d4fe973a069e528aba4d381.jpg",
      "batch": 2,
      "done": 0,
      "choice": ""
    }
  },
  {
    "pk": 241,
    "model": "accounts.task",
    "fields": {
      "lock": 3,
      "question": "7798e892c7e6cde0bab71cc8c8f2c593e2281f2ef218aeae719141eccfade061.jpg",
      "batch": 2,
      "done": 0,
      "choice": ""
    }
  },
  {
    "pk": 242,
    "model": "accounts.task",
    "fields": {
      "lock": 3,
      "question": "78a82c6f57ace3756a9bf9e6a3e3c98834834c9453b3d1b1142c4db8c99ab3cb.jpg",
      "batch": 2,
      "done": 0,
      "choice": ""
    }
  },
  {
    "pk": 243,
    "model": "accounts.task",
    "fields": {
      "lock": 3,
      "question": "79792a06135672865307a1412e432a7ce6a4aee9fdeb34f26a63bb5528eac2af.jpg",
      "batch": 2,
      "done": 0,
      "choice": ""
    }
  },
  {
    "pk": 244,
    "model": "accounts.task",
    "fields": {
      "lock": 3,
      "question": "7b77f88087968a1e00726a4fa4845c28d39e50e41d8def996106e17b7118c73e.jpg",
      "batch": 2,
      "done": 0,
      "choice": ""
    }
  },
  {
    "pk": 245,
    "model": "accounts.task",
    "fields": {
      "lock": 3,
      "question": "7d59bf0c48f7d456481b424ed541fa0726978e1893e782525349a96cc5171420.jpg",
      "batch": 2,
      "done": 0,
      "choice": ""
    }
  },
  {
    "pk": 246,
    "model": "accounts.task",
    "fields": {
      "lock": 3,
      "question": "7fda59bede08dfcf28a5bb9686385705d938e280eac20e64d5a9f5582cf6d453.jpg",
      "batch": 2,
      "done": 0,
      "choice": ""
    }
  },
  {
    "pk": 247,
    "model": "accounts.task",
    "fields": {
      "lock": 3,
      "question": "80188714d1d04fa612322c4b3f231b9deb91d19762c649c2c4ae0c94c7d1a7a2.jpg",
      "batch": 2,
      "done": 0,
      "choice": ""
    }
  },
  {
    "pk": 248,
    "model": "accounts.task",
    "fields": {
      "lock": 3,
      "question": "80a7bc1407b2d6a4acc774883bd9d870736c057e0993e07c7527d871586e7f41.jpg",
      "batch": 2,
      "done": 0,
      "choice": ""
    }
  },
  {
    "pk": 249,
    "model": "accounts.task",
    "fields": {
      "lock": 3,
      "question": "80ac96c42938454902e8b1cb9d2860b8346009b3a5445f352c56ffdb4858e7ef.jpg",
      "batch": 2,
      "done": 0,
      "choice": ""
    }
  },
  {
    "pk": 250,
    "model": "accounts.task",
    "fields": {
      "lock": 3,
      "question": "8215667cfc09c818d9f166eaf22288437e141b89636805e7332df622cf58d73a.jpg",
      "batch": 2,
      "done": 0,
      "choice": ""
    }
  },
  {
    "pk": 251,
    "model": "accounts.task",
    "fields": {
      "lock": 3,
      "question": "8727e6dd3fa702a64878c18de692a9e563fabced54dc1a68d2b4c0f406f68f76.jpg",
      "batch": 2,
      "done": 0,
      "choice": ""
    }
  },
  {
    "pk": 252,
    "model": "accounts.task",
    "fields": {
      "lock": 3,
      "question": "873b59fa4eb4c601c77909145a14026ac2574acb82ae4ffc19866f7932880d5c.jpg",
      "batch": 2,
      "done": 0,
      "choice": ""
    }
  },
  {
    "pk": 253,
    "model": "accounts.task",
    "fields": {
      "lock": 3,
      "question": "89122b0188e7a89b03ac2c1581a3d51d971bc85f6222d7a5e830cc2e5b539d4.jpg",
      "batch": 2,
      "done": 0,
      "choice": ""
    }
  },
  {
    "pk": 254,
    "model": "accounts.task",
    "fields": {
      "lock": 3,
      "question": "8da6b499a2fc53a2a133c2b56494e8d26b8afcbed30add126451e6615ade3c61.jpg",
      "batch": 2,
      "done": 0,
      "choice": ""
    }
  },
  {
    "pk": 255,
    "model": "accounts.task",
    "fields": {
      "lock": 3,
      "question": "8ff9dbaeac6ab6aa75e1c43db9d7fe6d472b0d25d17d5b291261cea81601f123.jpg",
      "batch": 2,
      "done": 0,
      "choice": ""
    }
  },
  {
    "pk": 256,
    "model": "accounts.task",
    "fields": {
      "lock": 3,
      "question": "903646afb75e3abc7b480131b2ebf9560a14d28b54ebd133424fcc13148c7afb.jpg",
      "batch": 2,
      "done": 0,
      "choice": ""
    }
  },
  {
    "pk": 257,
    "model": "accounts.task",
    "fields": {
      "lock": 3,
      "question": "9257b847c506a06c09dcde3b688d8651c6491c89aab1c6d160b99093f0276b10.jpg",
      "batch": 2,
      "done": 0,
      "choice": ""
    }
  },
  {
    "pk": 258,
    "model": "accounts.task",
    "fields": {
      "lock": 3,
      "question": "945258ad8175cca6f959e229ad0a5e9f2baeb5237e58bb18dbbbf33822ea7658.jpg",
      "batch": 2,
      "done": 0,
      "choice": ""
    }
  },
  {
    "pk": 259,
    "model": "accounts.task",
    "fields": {
      "lock": 3,
      "question": "98a26b2d1d661c243082ceba876a5e77f015d3bb08f4b8fb6292636e6e11088b.jpg",
      "batch": 2,
      "done": 0,
      "choice": ""
    }
  },
  {
    "pk": 260,
    "model": "accounts.task",
    "fields": {
      "lock": 3,
      "question": "992082370bfca2e99e2901baa9876624fef9b3bb8e3eebcdbe07bb0b158eb036.jpg",
      "batch": 2,
      "done": 0,
      "choice": ""
    }
  },
  {
    "pk": 261,
    "model": "accounts.task",
    "fields": {
      "lock": 3,
      "question": "9b92a81916ce094c0927779f8bc7227f3e99b71a19d402b3fc001b01af6671be.jpg",
      "batch": 2,
      "done": 0,
      "choice": ""
    }
  },
  {
    "pk": 262,
    "model": "accounts.task",
    "fields": {
      "lock": 3,
      "question": "9bc93376dbea5f26e53eea6ce098cb36300265e8b51fd190d97738ceb5a810b8.jpg",
      "batch": 2,
      "done": 0,
      "choice": ""
    }
  },
  {
    "pk": 263,
    "model": "accounts.task",
    "fields": {
      "lock": 3,
      "question": "9f1cccef099fcfa4599f5c99956d04ef80374e5913fb36ac3ea21174dd23b9ae.jpg",
      "batch": 2,
      "done": 0,
      "choice": ""
    }
  },
  {
    "pk": 264,
    "model": "accounts.task",
    "fields": {
      "lock": 3,
      "question": "a3e84e94a69acc9153f79650d78c143eb7549d975f6a30e6f369280ac899b7c9.jpg",
      "batch": 2,
      "done": 0,
      "choice": ""
    }
  },
  {
    "pk": 265,
    "model": "accounts.task",
    "fields": {
      "lock": 3,
      "question": "a4163e7ceac6fbfc7586217caea9698244402bc783f5dae66ee312fffc5d9427.jpg",
      "batch": 2,
      "done": 0,
      "choice": ""
    }
  },
  {
    "pk": 266,
    "model": "accounts.task",
    "fields": {
      "lock": 3,
      "question": "a9a5b50ba79615136df8ccf5300861eab34fa4d2c6d293012e394325ae4e9c73.jpg",
      "batch": 2,
      "done": 0,
      "choice": ""
    }
  },
  {
    "pk": 267,
    "model": "accounts.task",
    "fields": {
      "lock": 3,
      "question": "ab2cc7cc84b7bb7657b23d7a25f95643cab97e48a972971378b801da10b21a1a.jpg",
      "batch": 2,
      "done": 0,
      "choice": ""
    }
  },
  {
    "pk": 268,
    "model": "accounts.task",
    "fields": {
      "lock": 3,
      "question": "ae15d1ce9624e62a4d2834af1955ded0884d2c05e87b76084d6e7b59efc6e2a3.jpg",
      "batch": 2,
      "done": 0,
      "choice": ""
    }
  },
  {
    "pk": 269,
    "model": "accounts.task",
    "fields": {
      "lock": 3,
      "question": "ae393aedc879fcdbd0b220b31b02f3f5b08b6873f88f00a5f6257e48a7f00e81.jpg",
      "batch": 2,
      "done": 0,
      "choice": ""
    }
  },
  {
    "pk": 270,
    "model": "accounts.task",
    "fields": {
      "lock": 3,
      "question": "b66a2a8516d0c63e219efb5afda53aa7147b32ef2e625174421f85d35b115876.jpg",
      "batch": 2,
      "done": 0,
      "choice": ""
    }
  },
  {
    "pk": 271,
    "model": "accounts.task",
    "fields": {
      "lock": 3,
      "question": "b8d35454f1f6703ebaf708d4bd85f349d79c1ff23d9e12b724c42105242ed4bd.jpg",
      "batch": 2,
      "done": 0,
      "choice": ""
    }
  },
  {
    "pk": 272,
    "model": "accounts.task",
    "fields": {
      "lock": 3,
      "question": "bdd9921c80ec5551852da6fb00a72d5de25c4a23476a1e6cc064812572064aab.jpg",
      "batch": 2,
      "done": 0,
      "choice": ""
    }
  },
  {
    "pk": 273,
    "model": "accounts.task",
    "fields": {
      "lock": 3,
      "question": "c02d0fc8db91d202256c345a65aa52b5ca4c2ea1660df4cc432007ec4d7ecb00.jpg",
      "batch": 2,
      "done": 0,
      "choice": ""
    }
  },
  {
    "pk": 274,
    "model": "accounts.task",
    "fields": {
      "lock": 3,
      "question": "c077df1ebdc5624a57b6af250843559a57e591ab0e850a5bf97aac11a6dbbe54.jpg",
      "batch": 2,
      "done": 0,
      "choice": ""
    }
  },
  {
    "pk": 275,
    "model": "accounts.task",
    "fields": {
      "lock": 3,
      "question": "c0f2c260c8a4a1369ba2f1b948ef8877a5738c5753fcc218c8e440b5fa57eb48.jpg",
      "batch": 2,
      "done": 0,
      "choice": ""
    }
  },
  {
    "pk": 276,
    "model": "accounts.task",
    "fields": {
      "lock": 3,
      "question": "c13ed82cb3b7b7e23b74eb1c80c81048cc823ed4adbba6ad7491cb9aef039a43.jpg",
      "batch": 2,
      "done": 0,
      "choice": ""
    }
  },
  {
    "pk": 277,
    "model": "accounts.task",
    "fields": {
      "lock": 3,
      "question": "c2dc5a81ddf67880f25cfa2829b72d3ca496575f699a5a65fc6ebfa3ed2401e.jpg",
      "batch": 2,
      "done": 0,
      "choice": ""
    }
  },
  {
    "pk": 278,
    "model": "accounts.task",
    "fields": {
      "lock": 3,
      "question": "c622b9b881ddb80005d570395609a4f63626cfcf9600deff7db1b6c6ff42e515.jpg",
      "batch": 2,
      "done": 0,
      "choice": ""
    }
  },
  {
    "pk": 279,
    "model": "accounts.task",
    "fields": {
      "lock": 3,
      "question": "c75fb6057a3c37c165c19b648c200b0e8b81ba1965b105d39761d80076dbc735.jpg",
      "batch": 2,
      "done": 0,
      "choice": ""
    }
  },
  {
    "pk": 280,
    "model": "accounts.task",
    "fields": {
      "lock": 3,
      "question": "c9b633e326c4304f788c4a005949882f87f67a365b1ecfc480008f0169af01fa.jpg",
      "batch": 2,
      "done": 0,
      "choice": ""
    }
  },
  {
    "pk": 281,
    "model": "accounts.task",
    "fields": {
      "lock": 3,
      "question": "ca32d46beaa7548bb90ac37be18793d71de9fe460fe9463e27320c9b66af6244.jpg",
      "batch": 2,
      "done": 0,
      "choice": ""
    }
  },
  {
    "pk": 282,
    "model": "accounts.task",
    "fields": {
      "lock": 3,
      "question": "caac7045df06a3a2d1d2b7baf22423b59c4a9a1ab4b3bb68620f8b7e37b061ed.jpg",
      "batch": 2,
      "done": 0,
      "choice": ""
    }
  },
  {
    "pk": 283,
    "model": "accounts.task",
    "fields": {
      "lock": 3,
      "question": "cc07b04cccb92fb95a58a25299b5b2294b4b81aa28fdd601a0e1859a51bd3c63.jpg",
      "batch": 2,
      "done": 0,
      "choice": ""
    }
  },
  {
    "pk": 284,
    "model": "accounts.task",
    "fields": {
      "lock": 3,
      "question": "d1206bc4bca50ac9960b3b518035e7c4c6724689550c8b8667b437e5e3c04d58.jpg",
      "batch": 2,
      "done": 0,
      "choice": ""
    }
  },
  {
    "pk": 285,
    "model": "accounts.task",
    "fields": {
      "lock": 3,
      "question": "d2538d51e79d8dd2d3a93a358b99ca395ce7b838cc51f051535a49bd833b5a6c.jpg",
      "batch": 2,
      "done": 0,
      "choice": ""
    }
  },
  {
    "pk": 286,
    "model": "accounts.task",
    "fields": {
      "lock": 3,
      "question": "d2cdbf1e52f0d5fd44275559afe99bbfde3e6047dc21ecbb8fa0673309c742a1.jpg",
      "batch": 2,
      "done": 0,
      "choice": ""
    }
  },
  {
    "pk": 287,
    "model": "accounts.task",
    "fields": {
      "lock": 3,
      "question": "db22c9bb7fae1b27b5aae23a205701e377765513cab6bbc758a137261995ce99.jpg",
      "batch": 2,
      "done": 0,
      "choice": ""
    }
  },
  {
    "pk": 288,
    "model": "accounts.task",
    "fields": {
      "lock": 3,
      "question": "db636b8cb851fbf189931305f24d74861f154e3faa10441e838d6f7cd29464d2.jpg",
      "batch": 2,
      "done": 0,
      "choice": ""
    }
  },
  {
    "pk": 289,
    "model": "accounts.task",
    "fields": {
      "lock": 3,
      "question": "df3303d29b90bcd15af9dc1314c03b0e67c1b81534c060cf8e9ac10652c968f0.jpg",
      "batch": 2,
      "done": 0,
      "choice": ""
    }
  },
  {
    "pk": 290,
    "model": "accounts.task",
    "fields": {
      "lock": 3,
      "question": "df52501277aa94454873b4e3309e8b5d88906d51bdbb2d981b4a2f2367416573.jpg",
      "batch": 2,
      "done": 0,
      "choice": ""
    }
  },
  {
    "pk": 291,
    "model": "accounts.task",
    "fields": {
      "lock": 3,
      "question": "e1207b41b2e02aec061968c51b29533d4ea63975b057b665d956ac3d6b3c87bf.jpg",
      "batch": 2,
      "done": 0,
      "choice": ""
    }
  },
  {
    "pk": 292,
    "model": "accounts.task",
    "fields": {
      "lock": 3,
      "question": "e174495650ea91b47cd7550ea3c0bdc05431b9c934ec7c900609ef39cd3437fb.jpg",
      "batch": 2,
      "done": 0,
      "choice": ""
    }
  },
  {
    "pk": 293,
    "model": "accounts.task",
    "fields": {
      "lock": 3,
      "question": "e24c8c088489c8a5457c0573f092dd8b4f08ffffeae540eaf7ca89abd81399ba.jpg",
      "batch": 2,
      "done": 0,
      "choice": ""
    }
  },
  {
    "pk": 294,
    "model": "accounts.task",
    "fields": {
      "lock": 3,
      "question": "e53ecc2129fd4dfe44eea039bcadc3ea3882c93022cf00a6e30f73deeeee7b6a.jpg",
      "batch": 2,
      "done": 0,
      "choice": ""
    }
  },
  {
    "pk": 295,
    "model": "accounts.task",
    "fields": {
      "lock": 3,
      "question": "e6d934770597a823a589b6e9943dee715f953d2f0eee219a68150aa699338047.jpg",
      "batch": 2,
      "done": 0,
      "choice": ""
    }
  },
  {
    "pk": 296,
    "model": "accounts.task",
    "fields": {
      "lock": 3,
      "question": "e725301cff35bf897316a26806fdef914e60292ce79b3793c239c4080e324272.jpg",
      "batch": 2,
      "done": 0,
      "choice": ""
    }
  },
  {
    "pk": 297,
    "model": "accounts.task",
    "fields": {
      "lock": 3,
      "question": "e9160287e0bd8daf85f1fba36305f2177edebb759db3a24ef5624f25f1b2f5b7.jpg",
      "batch": 2,
      "done": 0,
      "choice": ""
    }
  },
  {
    "pk": 298,
    "model": "accounts.task",
    "fields": {
      "lock": 3,
      "question": "eb3817910fcd178e900740548e1458d138d6cfcbc4c3b167ebd4c6dbabb99460.jpg",
      "batch": 2,
      "done": 0,
      "choice": ""
    }
  },
  {
    "pk": 299,
    "model": "accounts.task",
    "fields": {
      "lock": 3,
      "question": "ec302a2cacdcb27f3fc630589ac81dfbcc9b1567d4eeed3a0938190188b5ca04.jpg",
      "batch": 2,
      "done": 0,
      "choice": ""
    }
  },
  {
    "pk": 300,
    "model": "accounts.task",
    "fields": {
      "lock": 3,
      "question": "ed74fbbf194ba3f7b4db2e2fa5e4b04be4da168619209cb66825fb329c10f80a.jpg",
      "batch": 2,
      "done": 0,
      "choice": ""
    }
  },
  {
    "pk": 301,
    "model": "accounts.task",
    "fields": {
      "lock": 3,
      "question": "f0710da32ee19cfdf11c9bd51db947cd3570426bddfd8d8a8e1b98d9914e0717.jpg",
      "batch": 2,
      "done": 0,
      "choice": ""
    }
  },
  {
    "pk": 302,
    "model": "accounts.task",
    "fields": {
      "lock": 3,
      "question": "f380f994ce14ec85a3263f602f179ff1a047dea0f5b07db2e48a7e595d3c66d8.jpg",
      "batch": 2,
      "done": 0,
      "choice": ""
    }
  },
  {
    "pk": 303,
    "model": "accounts.task",
    "fields": {
      "lock": 3,
      "question": "f540f2c823b972c7f1e78dca469d536ad55f251c53c6957f7172021f102e5abe.jpg",
      "batch": 2,
      "done": 0,
      "choice": ""
    }
  },
  {
    "pk": 304,
    "model": "accounts.task",
    "fields": {
      "lock": 3,
      "question": "f8ae98f001037dc909f16ef5bdd764a43cf577ce2540406eb4d05d87c20a9ec6.jpg",
      "batch": 2,
      "done": 0,
      "choice": ""
    }
  },
  {
    "pk": 305,
    "model": "accounts.task",
    "fields": {
      "lock": 3,
      "question": "fa5549d0c01c597812ffb342a6d141bb66b59b4544696fbd279adbbd2e921ebd.jpg",
      "batch": 2,
      "done": 0,
      "choice": ""
    }
  },
  {
    "pk": 306,
    "model": "accounts.task",
    "fields": {
      "lock": 3,
      "question": "fb309367ae15e282a50f091bb0920cff0b4719f685fa89a6bcbaf632476fb012.jpg",
      "batch": 2,
      "done": 0,
      "choice": ""
    }
  }
]
